fw_gear_image_pii_redactor/__init__.py
fw_gear_image_pii_redactor/main.py
fw_gear_image_pii_redactor/parser.py
fw_gear_image_pii_redactor/utility_helpers.py
fw_gear_image_pii_redactor-0.1.5.dist-info/LICENSE
fw_gear_image_pii_redactor-0.1.5.dist-info/METADATA
fw_gear_image_pii_redactor-0.1.5.dist-info/WHEEL
fw_gear_image_pii_redactor-0.1.5.dist-info/RECORD
